CHANGES.txt
README.txt
TODO.txt
bootstrap.py
buildout.cfg
setup.py
src/hurry/__init__.py
src/hurry.jqgrid.egg-info/PKG-INFO
src/hurry.jqgrid.egg-info/SOURCES.txt
src/hurry.jqgrid.egg-info/dependency_links.txt
src/hurry.jqgrid.egg-info/namespace_packages.txt
src/hurry.jqgrid.egg-info/not-zip-safe
src/hurry.jqgrid.egg-info/requires.txt
src/hurry.jqgrid.egg-info/top_level.txt
src/hurry/jqgrid/__init__.py
src/hurry/jqgrid/configure.zcml
src/hurry/jqgrid/jqgrid.txt
src/hurry/jqgrid/tests.py
src/hurry/jqgrid/jqgrid-build/css/ellipsis-xbl.xml
src/hurry/jqgrid/jqgrid-build/css/ui.jqgrid.css
src/hurry/jqgrid/jqgrid-build/js/Changes.txt
src/hurry/jqgrid/jqgrid-build/js/install.txt
src/hurry/jqgrid/jqgrid-build/js/jquery-1.3.2.min.js
src/hurry/jqgrid/jqgrid-build/js/jquery.jqGrid.min.js
src/hurry/jqgrid/jqgrid-build/js/i18n/grid.locale-bg.js
src/hurry/jqgrid/jqgrid-build/js/i18n/grid.locale-bg1251.js
src/hurry/jqgrid/jqgrid-build/js/i18n/grid.locale-cat.js
src/hurry/jqgrid/jqgrid-build/js/i18n/grid.locale-cn.js
src/hurry/jqgrid/jqgrid-build/js/i18n/grid.locale-cs.js
src/hurry/jqgrid/jqgrid-build/js/i18n/grid.locale-de.js
src/hurry/jqgrid/jqgrid-build/js/i18n/grid.locale-dk.js
src/hurry/jqgrid/jqgrid-build/js/i18n/grid.locale-el.js
src/hurry/jqgrid/jqgrid-build/js/i18n/grid.locale-en.js
src/hurry/jqgrid/jqgrid-build/js/i18n/grid.locale-fa.js
src/hurry/jqgrid/jqgrid-build/js/i18n/grid.locale-fi.js
src/hurry/jqgrid/jqgrid-build/js/i18n/grid.locale-fr.js
src/hurry/jqgrid/jqgrid-build/js/i18n/grid.locale-he.js
src/hurry/jqgrid/jqgrid-build/js/i18n/grid.locale-is.js
src/hurry/jqgrid/jqgrid-build/js/i18n/grid.locale-it.js
src/hurry/jqgrid/jqgrid-build/js/i18n/grid.locale-jp.js
src/hurry/jqgrid/jqgrid-build/js/i18n/grid.locale-nl.js
src/hurry/jqgrid/jqgrid-build/js/i18n/grid.locale-no.js
src/hurry/jqgrid/jqgrid-build/js/i18n/grid.locale-pl.js
src/hurry/jqgrid/jqgrid-build/js/i18n/grid.locale-pt-br.js
src/hurry/jqgrid/jqgrid-build/js/i18n/grid.locale-pt.js
src/hurry/jqgrid/jqgrid-build/js/i18n/grid.locale-ro.js
src/hurry/jqgrid/jqgrid-build/js/i18n/grid.locale-ru.js
src/hurry/jqgrid/jqgrid-build/js/i18n/grid.locale-sp.js
src/hurry/jqgrid/jqgrid-build/js/i18n/grid.locale-sv.js
src/hurry/jqgrid/jqgrid-build/js/i18n/grid.locale-tr.js
