Metadata-Version: 1.0
Name: hurry.jqgrid
Version: 3.6.2.0
Summary: hurry.resource style resources for jqgrid for jQuery.
Home-page: UNKNOWN
Author: Martijn Faassen
Author-email: faassen@startifact.com
License: ZPL 2.1 (jqgrid MIT/GPL)
Platform: UNKNOWN
